inserpa/__init__.py
inserpa/Interpolation/__init__.py
inserpa/Interpolation/color.py
inserpa/Interpolation/number.py
inserpa/Interpolation/text.py
inserpa/Utility/__init__.py
inserpa/Utility/color.py
inserpa/Utility/ease.py
inserpa/Utility/easing_functions.py
inserpa-1.0.0.dist-info/METADATA
inserpa-1.0.0.dist-info/WHEEL
inserpa-1.0.0.dist-info/top_level.txt
inserpa-1.0.0.dist-info/RECORD
